flaskuploadserver/__main__.py
flaskuploadserver-0.0.1.dist-info/METADATA
flaskuploadserver-0.0.1.dist-info/WHEEL
flaskuploadserver-0.0.1.dist-info/top_level.txt
flaskuploadserver-0.0.1.dist-info/RECORD
