Metadata-Version: 2.1
Name: flaskuploadserver
Version: 0.0.1
Summary: flask drag drop upload server
Author-email: Some Sysadmin <flaskupload@somesysadmin.com>
Project-URL: Homepage, https://example.com
Project-URL: Bug Tracker, https://example.com
Classifier: Programming Language :: Python :: 3
Classifier: License :: OSI Approved :: MIT License
Classifier: Operating System :: OS Independent
Requires-Python: >=3.7
Requires-Dist: Flask ==2.2.5
